{
  "leadId": "1570",
  "slug": "aggarwal-properties",
  "designation": "real estate",
  "name": "Aggarwal Properties",
  "businessType": "Property Dealer / Broker",
  "city": "New Delhi",
  "state": "Delhi",
  "tier": "Tier 1",
  "pincode": "110049",
  "address": "24 d, Squadron Leader Mohinder Kumar Jain Marg, near Father Agnel School, Gautam Nagar, New Delhi, Delhi 110049, India",
  "phone": "",
  "email": "",
  "website": "https://aggarwal-properties-frontend.vercel.app/",
  "googleMapsUrl": "https://maps.google.com/?cid=9658528136855202319"
}