{
  "leadId": "760",
  "slug": "aryabhatta-institute-of-mathematics",
  "designation": "education",
  "name": "ARYABHATTA INSTITUTE OF MATHEMATICS",
  "businessType": "Coaching Center / Tuition",
  "city": "Karimnagar",
  "state": "Telangana",
  "tier": "Tier 2",
  "pincode": "505001",
  "address": "C4Q7+WF8, near PARAMITA school, Mankamma Thota, Karimnagar, Telangana 505001, India",
  "phone": "",
  "email": "",
  "website": "",
  "googleMapsUrl": "https://maps.google.com/?cid=15879888210437656112"
}