{
  "leadId": "1875",
  "slug": "bajaj-electronics-warangal",
  "designation": "retail",
  "name": "Bajaj Electronics - Warangal",
  "businessType": "Electronics / Mobile Store",
  "city": "Warangal",
  "state": "Telangana",
  "tier": "Tier 2",
  "pincode": "506002",
  "address": "M/s SWARNA PALACE, D.No.11-23-892/1, Situated at, 23-947Near, Swarna palace, H.No 11, Narsampet Rd, LB Nagar, Warangal, Telangana 506002, India",
  "phone": "",
  "email": "",
  "website": "https://www.bajajelectronics.com/stores/telangana/warangal/warangal",
  "googleMapsUrl": "https://maps.google.com/?cid=1524056100625555431"
}