{
  "leadId": "4",
  "slug": "beta-digital-marketing-agency-in-bangalore",
  "designation": "it and technology",
  "name": "Beta Digital Marketing Agency in Bangalore",
  "businessType": "Digital Marketing Agency",
  "city": "Bangalore",
  "state": "Karnataka",
  "tier": "Tier 1",
  "pincode": "560027",
  "address": "372, 6th Cross Rd, Vinayaka Nagar, NGO Colony, Wilson Garden, Bengaluru, Karnataka 560027, India",
  "phone": "",
  "email": "",
  "website": "https://betadigitalmarketing.com/",
  "googleMapsUrl": "https://maps.google.com/?cid=4479055747644381323"
}