{
  "leadId": "402",
  "slug": "chennai-bike-service-cm-bike-point",
  "designation": "automotive",
  "name": "Chennai Bike Service - CM Bike Point",
  "businessType": "Car / Bike Service Center",
  "city": "Chennai",
  "state": "Tamil Nadu",
  "tier": "Tier 1",
  "pincode": "600087",
  "address": "No.146, Ramanujam St, Alwartirunagar, Chennai, Tamil Nadu 600087, India",
  "phone": "",
  "email": "",
  "website": "http://chennaibikeservice.com/",
  "googleMapsUrl": "https://maps.google.com/?cid=11060049679293650471"
}