{
  "leadId": "597",
  "slug": "clove-dental-clinic",
  "designation": "healthcare",
  "name": "Clove Dental Clinic",
  "businessType": "Dental Clinic",
  "city": "Hyderabad",
  "state": "Telangana",
  "tier": "Tier 1",
  "pincode": "500084",
  "address": "Sadanand Yadav Building, Masjid Banda Main Rd, near State Bank of India, Kondapur, NCB Enclave, Gachibowli, Hyderabad, Telangana 500084, India",
  "phone": "",
  "email": "",
  "website": "https://clovedental.in/dentist-near-me/hyderabad/clove-kondapur?utm_source=website&utm_medium=gmb&utm_campaign=Masjid_Banda_GMB_Hyderabad",
  "googleMapsUrl": "https://maps.google.com/?cid=17846223346719881314"
}