{
  "leadId": "1819",
  "slug": "genius-study-circle",
  "designation": "education",
  "name": "Genius Study Circle",
  "businessType": "Coaching Center / Tuition",
  "city": "Warangal",
  "state": "Telangana",
  "tier": "Tier 2",
  "pincode": "506001",
  "address": "5-10_100,1st floor gurumallu complex, Opposite Vagdevi Degree College, Kishanpura, Hanamkonda, Telangana 506001, India",
  "phone": "",
  "email": "",
  "website": "",
  "googleMapsUrl": "https://maps.google.com/?cid=18417056531542584685"
}