{
  "leadId": "717",
  "slug": "kims-beauty-salon-karimnagar",
  "designation": "beauty and wellness",
  "name": "Kims Beauty Salon Karimnagar",
  "businessType": "Beauty Salon / Parlour",
  "city": "Karimnagar",
  "state": "Telangana",
  "tier": "Tier 2",
  "pincode": "505001",
  "address": "1st Floor, Haina Complex, opp. Max Showroom, beside AXIS Bank, Mukarampura, Karimnagar, Telangana 505001, India",
  "phone": "",
  "email": "",
  "website": "http://www.kimsbeautysalons.com/",
  "googleMapsUrl": "https://maps.google.com/?cid=17955921529449206400"
}