{
  "leadId": "1099",
  "slug": "namak-indian-specialty-restaurant",
  "designation": "food and beverage",
  "name": "Namak - Indian Specialty Restaurant",
  "businessType": "Restaurant / Dine-in",
  "city": "Mumbai",
  "state": "Maharashtra",
  "tier": "Tier 1",
  "pincode": "400099",
  "address": "Hotel Sahara Star, opposite Terminal 1, Navpada, Vile Parle East, Vile Parle, Mumbai, Maharashtra 400099, India",
  "phone": "",
  "email": "",
  "website": "https://www.saharastar.com/dining/namak-indian-specialty.html",
  "googleMapsUrl": "https://maps.google.com/?cid=18157206871245264869"
}