{
  "leadId": "718",
  "slug": "naturals-family-salon-and-spa",
  "designation": "beauty and wellness",
  "name": "NATURALS family salon & spa",
  "businessType": "Beauty Salon / Parlour",
  "city": "Karimnagar",
  "state": "Telangana",
  "tier": "Tier 2",
  "pincode": "505001",
  "address": "Ground floor, Poulomi towers, near padmanayaka kalyana mandapam, Mukarampura, Karimnagar, Telangana 505001, India",
  "phone": "",
  "email": "",
  "website": "https://wa.me/918886281212",
  "googleMapsUrl": "https://maps.google.com/?cid=2381830201408214497"
}