{
  "leadId": "1226",
  "slug": "niramaya-medical-care",
  "designation": "healthcare",
  "name": "NIRAMAYA MEDICAL CARE",
  "businessType": "General Clinic / Polyclinic",
  "city": "Mysore",
  "state": "Karnataka",
  "tier": "Tier 1",
  "pincode": "570009",
  "address": "Diya Arcade, Kantharaja Urs Rd, K.G Koppal, Kukkarahalli, Saraswathipuram, Mysuru, Karnataka 570009, India",
  "phone": "",
  "email": "",
  "website": "https://niramayamedicalcare.com/",
  "googleMapsUrl": "https://maps.google.com/?cid=15185936940382880884"
}