{
  "leadId": "272",
  "slug": "partha-dental-clinic-jayanagar-bangalore-invisalign-provider-braces-root-canal-and-dental-implants",
  "designation": "healthcare",
  "name": "Partha Dental Clinic - Jayanagar, Bangalore | Invisalign Provider | Braces, Root Canal & Dental Implants",
  "businessType": "Dental Clinic",
  "city": "Bangalore",
  "state": "Karnataka",
  "tier": "Tier 1",
  "pincode": "560041",
  "address": "beside Ragigudda Arch, near Bus Stop, 2nd Phase, Jayanagar, Bengaluru, Karnataka 560041, India",
  "phone": "",
  "email": "",
  "website": "https://parthadental.com/dental-skin-hair-clinic-jayanagar/?utm_source=google&utm_medium=gmb&utm_campaign=jayanagar",
  "googleMapsUrl": "https://maps.google.com/?cid=12990940890814054409"
}