{
  "leadId": "1150",
  "slug": "river-service-vidyaranyapura",
  "designation": "automotive",
  "name": "River Service Vidyaranyapura",
  "businessType": "Car / Bike Service Center",
  "city": "Mysore",
  "state": "Karnataka",
  "tier": "Tier 1",
  "pincode": "570008",
  "address": "436, 4th Main 17th Cross Rd, Industrial Suburb, Vidyaranyapura, Visveshwara Nagar, Mysuru, Karnataka 570008, India",
  "phone": "",
  "email": "",
  "website": "https://www.rideriver.com/",
  "googleMapsUrl": "https://maps.google.com/?cid=15688115882360945101"
}