{
  "leadId": "345",
  "slug": "roof-360-real-estate-and-properties",
  "designation": "real estate",
  "name": "Roof 360 Real Estate and Properties",
  "businessType": "Property Dealer / Broker",
  "city": "Bangalore",
  "state": "Karnataka",
  "tier": "Tier 1",
  "pincode": "560005",
  "address": "No. 68/1, 2nd Floor, Coles Rd, Cleveland Town, Fraser Town, Bengaluru, Karnataka 560005, India",
  "phone": "",
  "email": "",
  "website": "http://www.roof360.in/",
  "googleMapsUrl": "https://maps.google.com/?cid=132706764891728512"
}