{
  "leadId": "1140",
  "slug": "royal-enfield-service-center-aadith-motors",
  "designation": "automotive",
  "name": "Royal Enfield Service Center - Aadith Motors",
  "businessType": "Car / Bike Service Center",
  "city": "Mysore",
  "state": "Karnataka",
  "tier": "Tier 1",
  "pincode": "570017",
  "address": "Shop No 881, Aadith Motors, Hunsur Main Rd, 1st Stage, Vijayanagar 1st Stage, Vijayanagar, Mysuru, Karnataka 570017, India",
  "phone": "",
  "email": "",
  "website": "https://www.royalenfield.com/?utm_source=GMBlisting&utm_medium=organic",
  "googleMapsUrl": "https://maps.google.com/?cid=13783718639487813943"
}