{
  "leadId": "414",
  "slug": "shikshaa-coaching-centre-cbse-state-board-icse-maths-science-accounts-college-madras-university-nios",
  "designation": "education",
  "name": "Shikshaa Coaching Centre - CBSE | State Board | ICSE | Maths | Science | Accounts | College, Madras University, NIOS",
  "businessType": "Coaching Center / Tuition",
  "city": "Chennai",
  "state": "Tamil Nadu",
  "tier": "Tier 1",
  "pincode": "600001",
  "address": "2 Mulla Sahib Ln Opposite:, Opposite: TTV School, Gujarati Wadi Temple, Mint St, Sowcarpet, George Town, Chennai, Tamil Nadu 600001, India",
  "phone": "",
  "email": "",
  "website": "",
  "googleMapsUrl": "https://maps.google.com/?cid=7508604978666923834"
}