{
  "leadId": "1009",
  "slug": "taj-tutorials",
  "designation": "education",
  "name": "TAJ TUTORIALS",
  "businessType": "Coaching Center / Tuition",
  "city": "Mumbai",
  "state": "Maharashtra",
  "tier": "Tier 1",
  "pincode": "400003",
  "address": "284, Sardar Vallabhbhai Patel Rd, below Diamond Jubilee Girls School, Dongri, Umerkhadi, Mumbai, Maharashtra 400003, India",
  "phone": "",
  "email": "",
  "website": "https://sites.google.com/view/tajtutorials2006-com/home",
  "googleMapsUrl": "https://maps.google.com/?cid=11713157298177652751"
}