{
  "leadId": "1121",
  "slug": "toniandguy-hairdressing-salon-gokulam-mysuru",
  "designation": "beauty and wellness",
  "name": "Toni&Guy Hairdressing Salon, Gokulam, Mysuru",
  "businessType": "Beauty Salon / Parlour",
  "city": "Mysore",
  "state": "Karnataka",
  "tier": "Tier 1",
  "pincode": "570002",
  "address": "1st Floor, Toni and Guy, Gokulam Main Rd, opposite Starbucks and, next to cubs, Vani Vilas Mohalla, Mysuru, Karnataka 570002, India",
  "phone": "",
  "email": "",
  "website": "https://www.instagram.com/toniandguymysuru",
  "googleMapsUrl": "https://maps.google.com/?cid=57129322576787872"
}