{
  "leadId": "350",
  "slug": "topline-estates",
  "designation": "real estate",
  "name": "TOPLINE ESTATES",
  "businessType": "Property Dealer / Broker",
  "city": "Bangalore",
  "state": "Karnataka",
  "tier": "Tier 1",
  "pincode": "560084",
  "address": "costa square, 80/2 D, North Rd, C K Gardens, Thomas Town, Cooke Town, Bengaluru, Karnataka 560084, India",
  "phone": "",
  "email": "",
  "website": "http://www.toplineestates.com/",
  "googleMapsUrl": "https://maps.google.com/?cid=1303827985305447219"
}