{
  "leadId": "1142",
  "slug": "valvoline-bike-xpert-mahalakshmi-auto-works",
  "designation": "automotive",
  "name": "Valvoline Bike Xpert - Mahalakshmi Auto Works",
  "businessType": "Car / Bike Service Center",
  "city": "Mysore",
  "state": "Karnataka",
  "tier": "Tier 1",
  "pincode": "570008",
  "address": "5, 2nd Main, 16th Cross Rd, opposite Boothala Pitch Play Ground, Vidyaranyapura, Mysuru, Visveshwara Nagar, Karnataka 570008, India",
  "phone": "",
  "email": "",
  "website": "https://www.valvoline.com/en-in?utm_source=locator&utm_medium=googleplaces",
  "googleMapsUrl": "https://maps.google.com/?cid=12697413714188717143"
}