{
  "leadId": "1433",
  "slug": "yamaha-motor-showroom-nalgonda-munna-motors",
  "designation": "automotive",
  "name": "Yamaha Motor Showroom | Nalgonda - Munna Motors",
  "businessType": "Two-Wheeler Dealership",
  "city": "Nalgonda",
  "state": "Telangana",
  "tier": "Tier 2",
  "pincode": "508001",
  "address": "Padma Nagar, Nalgonda, Telangana 508001, India",
  "phone": "",
  "email": "",
  "website": "https://munnaunitedmotors.in/",
  "googleMapsUrl": "https://maps.google.com/?cid=5796121316417148189"
}